<?xml version="1.0" encoding="UTF-8"?>
<bundle>
  <!--
  #####################################################################
  # org.exoplatform.ecm.webui.tree.selectmany.UICategoriesSelectPanel #
  #####################################################################
  -->
  <UITreeList>
    <header>
      <name>???</name>
      <action>?????</action>
    </header>
    <action />
    <info>
      <child-not-found>????? ??? ?????!</child-not-found>
    </info>
  </UITreeList>
  <!--
  ######################################################################
  # org.exoplatform.ecm.webui.tree.selectmany.UISelectedCategoriesGrid #
  ######################################################################
  -->
  <UISelectedCategoriesGrid>
    <header>
      <categoryName>??? ?????</categoryName>
      <categoryPath>??? ??????</categoryPath>
      <action>????</action>
    </header>
    <action>
      <SaveCategories>????</SaveCategories>
      <Cancel>?????</Cancel>
    </action>
    <msg>
      <cannot-save>.?????? ??? ??????</cannot-save>
      <have-saved>?????? ?????? ?????</have-saved>
      <non-categories>.???? ?????. ?????? ?????? ???? ????</non-categories>
      <confirm-delete>?? ???? ??? ??? ?????</confirm-delete>
    </msg>
  </UISelectedCategoriesGrid>
  <!--
  ######################################################################
  #	 org.exoplatform.ecm.webui.selector.UIPermissionSelector           #
  ######################################################################
  -->
  <SelectUserOrGroup>
    <title>
      <UIPermissionUser>?????? ????????</UIPermissionUser>
      <UIPermissionMembership>?????????????</UIPermissionMembership>
    </title>
  </SelectUserOrGroup>
  <UIPermissionUser>
    <label>
      <selectUser>?????? ????????</selectUser>
      <selectGroup>???? ????? ??????</selectGroup>
    </label>
  </UIPermissionUser>
  <UIPermissionMembership>
    <label>
      <selectUser>?????????????</selectUser>
      <selectGroup>???? ????? ??????</selectGroup>
    </label>
  </UIPermissionMembership>
</bundle>
